lesscode_utils/__init__.py
lesscode_utils/airflow_utils.py
lesscode_utils/common_utils.py
lesscode_utils/company_es_utils.py
lesscode_utils/const_utils.py
lesscode_utils/date_time_utils.py
lesscode_utils/es_utils.py
lesscode_utils/geo_utils.py
lesscode_utils/json_utils.py
lesscode_utils/mongo_util.py
lesscode_utils/my_dict.py
lesscode_utils/request.py
lesscode_utils/single_instance_utils.py
lesscode_utils/sqlalchemy_utils.py
lesscode_utils/thread_task.py
lesscode_utils/version.py
lesscode_utils/wrapper.py
lesscode_utils/NestedUtils/NestedUtils.py
lesscode_utils/NestedUtils/__init__.py
lesscode_utils/NestedUtils/nested_ddl.py
lesscode_utils/encryption_algorithm/__init__.py
lesscode_utils/encryption_algorithm/aes.py
lesscode_utils/encryption_algorithm/base64.py
lesscode_utils/encryption_algorithm/des.py
lesscode_utils/encryption_algorithm/hmac.py
lesscode_utils/encryption_algorithm/md5.py
lesscode_utils/encryption_algorithm/rsa.py
lesscode_utils/encryption_algorithm/sha1.py
lesscode_utils/encryption_algorithm/sha256.py
lesscode_utils/encryption_algorithm/smx.py
lesscode_utils/oss/__init__.py
lesscode_utils/oss/aliyun_oss.py
lesscode_utils/oss/ks3_oss.py
lesscode_utils-0.0.92.dist-info/METADATA
lesscode_utils-0.0.92.dist-info/WHEEL
lesscode_utils-0.0.92.dist-info/top_level.txt
lesscode_utils-0.0.92.dist-info/RECORD
