Metadata-Version: 2.1
Name: lesscode_utils
Version: 0.0.92
Summary: lesscode_utils是通用工具包
Author: Chao.yy
Author-email: yuyc@ishangqi.com
Platform: python
Classifier: Programming Language :: Python :: 3
Classifier: Operating System :: OS Independent
Requires-Python: >=3.6
